sphinx_autodoc_defaultargs.py
sphinx_autodoc_defaultargs-0.1.2.dist-info/LICENSE
sphinx_autodoc_defaultargs-0.1.2.dist-info/METADATA
sphinx_autodoc_defaultargs-0.1.2.dist-info/WHEEL
sphinx_autodoc_defaultargs-0.1.2.dist-info/top_level.txt
sphinx_autodoc_defaultargs-0.1.2.dist-info/RECORD
