Metadata-Version: 2.1
Name: sphinx-autodoc-defaultargs
Version: 0.1.2
Summary: Automatic generation of default arguments for the Sphinx autodoc extension.
Home-page: UNKNOWN
Author: Zhi Wang
Author-email: zhiwang@uchicago.edu
License: MIT
Project-URL: Source code, https://github.com/zwang123/sphinx-autodoc-defaultargs
Project-URL: Issue tracker, https://github.com/zwang123/sphinx-autodoc-defaultargs/issues
Platform: UNKNOWN
Classifier: Development Status :: 3 - Alpha
Classifier: Framework :: Sphinx :: Extension
Classifier: Intended Audience :: Developers
Classifier: License :: OSI Approved :: MIT License
Classifier: Framework :: Sphinx :: Extension
Classifier: Topic :: Documentation :: Sphinx
Classifier: Programming Language :: Python
Classifier: Programming Language :: Python :: 3
Classifier: Programming Language :: Python :: 3.5
Classifier: Programming Language :: Python :: 3.6
Classifier: Programming Language :: Python :: 3.7
Classifier: Programming Language :: Python :: 3.8
Classifier: Programming Language :: Python :: 3.9
Classifier: Programming Language :: Python :: 3.10
Requires-Python: >=3.5
Requires-Dist: Sphinx (>=3.0)
Provides-Extra: test
Requires-Dist: pytest (>=3.1.0) ; extra == 'test'
Requires-Dist: typing-extensions (>=3.5) ; extra == 'test'
Requires-Dist: sphobjinv (>=2.0) ; extra == 'test'
Requires-Dist: Sphinx (>=3.2.0) ; extra == 'test'
Requires-Dist: dataclasses ; (python_version == "3.6") and extra == 'test'
Provides-Extra: type_comments
Requires-Dist: typed-ast (>=1.4.0) ; (python_version < "3.8") and extra == 'type_comments'
